{
  "id": "e9522cd24df54d29a48b6af683efd9c7",
  "semantic_identifier": "Service Usage Data for 2025-12-17.docx",
  "title": null,
  "source": "google_doc",
  "doc_updated_at": "2025-12-17",
  "metadata": {
    "owner_names": ""
  },
  "doc_metadata": {
    "hierarchy": {
      "source_path": [
        "My Drive"
      ],
      "drive_id": null,
      "file_name": "Service Usage Data for 2025-12-17.docx",
      "mime_type": "application/vnd.openxmlformats-officedocument.wordprocessingml.document"
    }
  },
  "sections": [
    {
      "text": "[{'account': 'Vividcedar Marketing', 'value': 0.6118132470696251, 'day': 246}, {'account': 'Jadecircuit Electronics', 'value': 1.0254235621912189, 'day': 257}, {'account': 'Firefly Meridian Labs', 'value': 0.804577196256169, 'day': 11}, {'account': 'Xenith Argo Logistics', 'value': -0.12117577515920275, 'day': 118}, {'account': 'Wavelink Marine Systems', 'value': 0.33033221111202715, 'day': 126}, {'account': 'Indigoriver Ventures', 'value': 0.8922600233006243, 'day': 77}, {'account': 'Velvetcompass Travel', 'value': 2.3676313859630183, 'day': 2}, {'account': 'Northwind Parcel Services', 'value': -0.25607900426760305, 'day': 209}, {'account': 'Pebble & Pine Coffee', 'value': 2.167397668258004, 'day': 86}, {'account': 'Zephyrroot Materials', 'value': 0.9365251083006263, 'day': 28}, {'account': 'Alpinequill Publishing', 'value': 1.4084965156893483, 'day': 47}, {'account': 'Terraspire Energy', 'value': 1.78504094634371, 'day': 46}, {'account': 'Marinerock Outdoor Gear', 'value': 2.3028464500678227, 'day': 153}, {'account': 'Xylembright Water Tech', 'value': 0.39494200083526704, 'day': 27}]",
      "link": "https://www.onyx.app/93991"
    }
  ],
  "primary_owners": [],
  "secondary_owners": []
}